[
    {
        "folder": "keyword-of-modern-development",
        "name": "モダン開発をかじってみる",
        "date": "2017-08-25",
        "description": "最近の開発のトレンド等についての話．大学の合宿にて発表しました",
        "format": "pdf"
    },
    {
        "folder": "programming-beginner-tips",
        "name": "プログラマ初心者向けのTips",
        "description": "サークルで発表したものです。",
        "date": "2016-06-20",
        "format": "web(reveal.js)"
    },
    {
        "folder": "self-introduction",
        "name": "自己紹介スライド",
        "date": "2016-05-07",
        "description": "大学のサークルにて行われた自己紹介プレゼン大会にて発表したものです。",
        "format": "web"
    }
]